EasyMarkdown/MD_codeblock_list.py
EasyMarkdown/__init__.py
EasyMarkdown/easy_Markdown.py
EasyMarkdown-0.1.1.dist-info/LICENSE
EasyMarkdown-0.1.1.dist-info/METADATA
EasyMarkdown-0.1.1.dist-info/WHEEL
EasyMarkdown-0.1.1.dist-info/top_level.txt
EasyMarkdown-0.1.1.dist-info/RECORD
