Metadata-Version: 2.1
Name: EasyMarkdown
Version: 0.1.1
Summary: You can easily generate markdowns in python.
Author-email: shotaro <taro06360@gmail.com>
Project-URL: Homepage, https://github.com/tarou-imokenpi/EasyMarkdown
Project-URL: Bug Tracker, https://github.com/tarou-imokenpi/EasyMarkdown/issues
Classifier: Programming Language :: Python :: 3
Classifier: License :: OSI Approved :: MIT License
Classifier: Operating System :: OS Independent
Requires-Python: >=3.7
License-File: LICENSE
